plexorank/__init__.py
plexorank/cipher_tables.py
plexorank/rank.py
plexorank/utils.py
plexorank-0.0.9.dist-info/METADATA
plexorank-0.0.9.dist-info/WHEEL
plexorank-0.0.9.dist-info/licenses/LICENSE
plexorank-0.0.9.dist-info/RECORD
