Metadata-Version: 2.1
Name: plexorank
Version: 0.0.9
Summary: A lexicographical ranking system for python
Project-URL: Homepage, https://github.com/subtleco/pylex
Project-URL: Bug Tracker, https://github.com/subtleco/pylex/issues
Author-email: Alex Martin <raymond.alex.martin@gmail.com>
License-File: LICENSE
Classifier: License :: OSI Approved :: MIT License
Classifier: Operating System :: OS Independent
Classifier: Programming Language :: Python :: 3
Requires-Python: >=3.7
